ddb/__init__.py
ddb/__main__.py
ddb/__version__.py
ddb/registry.py
ddb/action/__init__.py
ddb/action/action.py
ddb/action/runner.py
ddb/action/runnerfactory.py
ddb/binary/__init__.py
ddb/binary/binary.py
ddb/cache/__init__.py
ddb/cache/cache.py
ddb/cache/removal.py
ddb/cache/shelve_cache.py
ddb/command/__init__.py
ddb/command/command.py
ddb/config/__init__.py
ddb/config/config.py
ddb/config/flatten.py
ddb/config/merger.py
ddb/config/migrations.py
ddb/context/__init__.py
ddb/context/context.py
ddb/event/__init__.py
ddb/event/bus.py
ddb/event/events.py
ddb/feature/__init__.py
ddb/feature/bootstrap.py
ddb/feature/feature.py
ddb/feature/schema.py
ddb/feature/certs/__init__.py
ddb/feature/certs/actions.py
ddb/feature/certs/schema.py
ddb/feature/certs/cfssl/__init__.py
ddb/feature/certs/cfssl/checksums.py
ddb/feature/certs/cfssl/crypto.py
ddb/feature/certs/cfssl/writer.py
ddb/feature/cookiecutter/__init__.py
ddb/feature/cookiecutter/actions.py
ddb/feature/cookiecutter/schema.py
ddb/feature/copy/__init__.py
ddb/feature/copy/actions.py
ddb/feature/copy/schema.py
ddb/feature/core/__init__.py
ddb/feature/core/actions.py
ddb/feature/core/schema.py
ddb/feature/docker/__init__.py
ddb/feature/docker/actions.py
ddb/feature/docker/binaries.py
ddb/feature/docker/schema.py
ddb/feature/docker/utils.py
ddb/feature/docker/lib/compose/__init__.py
ddb/feature/docker/lib/compose/config/__init__.py
ddb/feature/docker/lib/compose/config/errors.py
ddb/feature/docker/lib/compose/config/types.py
ddb/feature/file/__init__.py
ddb/feature/file/actions.py
ddb/feature/file/schema.py
ddb/feature/fixuid/__init__.py
ddb/feature/fixuid/actions.py
ddb/feature/fixuid/schema.py
ddb/feature/git/__init__.py
ddb/feature/git/actions.py
ddb/feature/git/schema.py
ddb/feature/gitignore/__init__.py
ddb/feature/gitignore/actions.py
ddb/feature/gitignore/schema.py
ddb/feature/jinja/__init__.py
ddb/feature/jinja/actions.py
ddb/feature/jinja/filters.py
ddb/feature/jinja/schema.py
ddb/feature/jinja/tests.py
docker_devbox_ddb-3.1.0.dist-info/LICENSE
docker_devbox_ddb-3.1.0.dist-info/METADATA
docker_devbox_ddb-3.1.0.dist-info/WHEEL
docker_devbox_ddb-3.1.0.dist-info/entry_points.txt
docker_devbox_ddb-3.1.0.dist-info/top_level.txt
docker_devbox_ddb-3.1.0.dist-info/zip-safe
docker_devbox_ddb-3.1.0.dist-info/RECORD
