Metadata-Version: 2.1
Name: docker-devbox-ddb
Version: 3.1.0
Summary: ddb - Erase environment differences, make developers happy !
Home-page: https://github.com/inetum-orleans/docker-devbox-ddb
Download-URL: https://pypi.python.org/packages/source/g/docker-devbox-ddb/docker-devbox-ddb-3.1.0.tar.gz
Author: Rémi Alvergnat
Author-email: remi.alvergnat@gfi.world
License: MIT
Keywords: docker docker-compose development environment devops templates jsonnet jinja watch
Classifier: Development Status :: 5 - Production/Stable
Classifier: License :: OSI Approved :: MIT License
Classifier: Operating System :: OS Independent
Classifier: Intended Audience :: Developers
Classifier: Programming Language :: Python :: 3
Classifier: Programming Language :: Python :: 3.8
Classifier: Programming Language :: Python :: 3.9
Classifier: Programming Language :: Python :: 3.10
Classifier: Programming Language :: Python :: 3.11
Classifier: Topic :: Software Development :: Libraries :: Python Modules
License-File: LICENSE
Requires-Dist: colorama
Requires-Dist: colorlog
Requires-Dist: verboselogs
Requires-Dist: netifaces
Requires-Dist: requests
Requires-Dist: PyYAML
Requires-Dist: marshmallow
Requires-Dist: dotty-dict
Requires-Dist: deepmerge
Requires-Dist: diskcache
Requires-Dist: python-slugify
Requires-Dist: dictdiffer
Requires-Dist: Jinja2
Requires-Dist: braceexpand
Requires-Dist: toposort
Requires-Dist: cookiecutter
Requires-Dist: jsonnet-binary
Requires-Dist: zgitignore
Requires-Dist: cached-property
Requires-Dist: dockerfile-parse
Requires-Dist: cfssl>=0.0.3b243
Requires-Dist: cryptography
Requires-Dist: watchdog==4.0.2
Requires-Dist: gitpython
Requires-Dist: chmod-monkey>=1.1.1
Requires-Dist: paramiko
Requires-Dist: wcmatch
Requires-Dist: marshmallow-union
Requires-Dist: progress
Requires-Dist: ordered-set
Requires-Dist: patch
Requires-Dist: semver
Requires-Dist: distro
Requires-Dist: python-on-whales
Provides-Extra: dev
Requires-Dist: python-semantic-release<8; extra == "dev"
Requires-Dist: pyinstaller; extra == "dev"
Requires-Dist: commitizen; extra == "dev"
Requires-Dist: pre-commit; extra == "dev"
Requires-Dist: tox; extra == "dev"
Requires-Dist: astroid; extra == "dev"
Requires-Dist: pylint; extra == "dev"
Requires-Dist: docker[tls]; extra == "dev"
Requires-Dist: pytest==7.4.4; extra == "dev"
Requires-Dist: coverage; extra == "dev"
Requires-Dist: waiting; extra == "dev"
Requires-Dist: pytest-mock; extra == "dev"
Requires-Dist: pytest-cov; extra == "dev"
Requires-Dist: pytest-benchmark; extra == "dev"
Requires-Dist: pytest-profiling; extra == "dev"
Requires-Dist: responses; extra == "dev"
Requires-Dist: pex; extra == "dev"
